stackify/__init__.py
stackify/cli.py
stackify/stackify.py
stackify/ansible/main.yml
stackify/ansible/group_vars/all.yml
stackify/ansible/modules/ansible/ansible.vars.yml
stackify/ansible/modules/ansible/ansible.yml
stackify/ansible/modules/docker/docker.darwin.yml
stackify/ansible/modules/docker/docker.debian.yml
stackify/ansible/modules/docker/docker.vars.yml
stackify/ansible/modules/docker/docker.yml
stackify/ansible/modules/git/git.darwin.yml
stackify/ansible/modules/git/git.debian.yml
stackify/ansible/modules/git/git.yml
stackify/ansible/modules/mysql/mysql.darwin.yml
stackify/ansible/modules/mysql/mysql.debian.yml
stackify/ansible/modules/mysql/mysql.yml
stackify/ansible/modules/orbstack/orbstack.darwin.yml
stackify/ansible/modules/orbstack/orbstack.yml
stackify/ansible/modules/postgresql/postgresql.darwin.yml
stackify/ansible/modules/postgresql/postgresql.debian.yml
stackify/ansible/modules/postgresql/postgresql.yml
stackify/ansible/modules/pyenv/pyenv.darwin.yml
stackify/ansible/modules/pyenv/pyenv.debian.yml
stackify/ansible/modules/pyenv/pyenv.yml
stackify/ansible/modules/python/python.install.yml
stackify/ansible/modules/python/python.vars.yml
stackify/ansible/modules/python/python.yml
stackify/ansible/modules/rbenv/rbenv.darwin.yml
stackify/ansible/modules/rbenv/rbenv.debian.yml
stackify/ansible/modules/rbenv/rbenv.yml
stackify/ansible/modules/redis/redis.darwin.yml
stackify/ansible/modules/redis/redis.debian.yml
stackify/ansible/modules/redis/redis.yml
stackify/ansible/modules/ruby/ruby.install.yml
stackify/ansible/modules/ruby/ruby.vars.yml
stackify/ansible/modules/ruby/ruby.yml
stackify/ansible/modules/stackify/stackify.yml
stackify/ansible/tasks/darwin.yml
stackify/ansible/tasks/debian.yml
stackify-0.0.10.dist-info/LICENSE
stackify-0.0.10.dist-info/METADATA
stackify-0.0.10.dist-info/WHEEL
stackify-0.0.10.dist-info/entry_points.txt
stackify-0.0.10.dist-info/top_level.txt
stackify-0.0.10.dist-info/RECORD
