Metadata-Version: 2.1
Name: stackify
Version: 0.0.10
Summary: Simplify developer environment setup
Author-email: David Rice <me@davidjrice.co.uk>
License: MIT License
Project-URL: Homepage, https://github.com/davidjrice/stackify
Project-URL: Bug Tracker, https://github.com/davidjrice/stackify/issues
Classifier: Programming Language :: Python :: 3
Classifier: License :: OSI Approved :: MIT License
Classifier: Operating System :: OS Independent
Requires-Python: >=3.10
License-File: LICENSE
Requires-Dist: ansible-core ==2.16.0
Requires-Dist: ansible-runner ==2.3.4
Requires-Dist: commitizen ==3.12.0
